understory/apps/indieauth_server/__init__.py
understory/apps/indieauth_server/templates/__init__.py
understory/apps/indieauth_server/templates/authorizations.html
understory/apps/indieauth_server/templates/client.html
understory/apps/indieauth_server/templates/clients.html
understory/apps/indieauth_server/templates/consent.html
understory/apps/indieauth_server/templates/root.html
understory/apps/indieauth_server/templates/unauthorized.html
understory_indieauth_server-0.0.6.dist-info/entry_points.txt
understory_indieauth_server-0.0.6.dist-info/LICENSE
understory_indieauth_server-0.0.6.dist-info/WHEEL
understory_indieauth_server-0.0.6.dist-info/METADATA
understory_indieauth_server-0.0.6.dist-info/RECORD
